tempvars/__init__.py
tempvars/tempvars.py
tempvars-1.0.1.dist-info/LICENSE.txt
tempvars-1.0.1.dist-info/METADATA
tempvars-1.0.1.dist-info/WHEEL
tempvars-1.0.1.dist-info/top_level.txt
tempvars-1.0.1.dist-info/RECORD
