Metadata-Version: 2.1
Name: tempvars
Version: 1.0.1
Summary: Context manager for handling temporary variables in Jupyter Notebook, IPython, etc.
Home-page: https://www.github.com/bskinn/tempvars
Author: Brian Skinn
Author-email: bskinn@alum.mit.edu
License: MIT License
Platform: UNKNOWN
Classifier: License :: OSI Approved :: MIT License
Classifier: Natural Language :: English
Classifier: Intended Audience :: Science/Research
Classifier: Intended Audience :: Developers
Classifier: Operating System :: OS Independent
Classifier: Programming Language :: Python :: 3
Classifier: Programming Language :: Python :: 3 :: Only
Classifier: Programming Language :: Python :: 3.4
Classifier: Programming Language :: Python :: 3.5
Classifier: Programming Language :: Python :: 3.6
Classifier: Programming Language :: Python :: 3.7
Classifier: Topic :: Software Development
Classifier: Development Status :: 5 - Production/Stable
Requires: attrs (>=17.1)
Provides: tempvars
Requires-Python: >=3.4
Requires-Dist: attrs (>=17)
